<?xml version="1.0" encoding="utf-8"?>
<mets:mets xmlns:mets="http://www.loc.gov/METS/" xmlns:rights="http://www.loc.gov/rights/" xmlns:xlink="http://www.w3.org/1999/xlink" xmlns:lc="http://www.loc.gov/mets/profiles" xmlns:bib="http://www.loc.gov/mets/profiles/bibRecord" xmlns:mods="http://www.loc.gov/mods/v3" xmlns:xsi="http://www.w3.org/2001/XMLSchema-instance" OBJID="loc.afc.afc9999005.1153" xsi:schemaLocation="http://www.loc.gov/METS/ http://www.loc.gov/standards/mets/mets.xsd http://www.loc.gov/mods/v3 http://www.loc.gov/standards/mods/v3/mods-3-2.xsd">
  <mets:metsHdr ID="GUB0102021" CREATEDATE="2014-05-16T10:57:00" LASTMODDATE="2014-08-29T13:53:12" RECORDSTATUS="complete">
    <mets:agent ROLE="CREATOR" TYPE="ORGANIZATION" ID="Gdig">
      <mets:name>GUB, Göteborgs universitetsbibliotek, Digitala tjänster</mets:name>
    </mets:agent>
    <mets:agent ROLE="ARCHIVIST" TYPE="ORGANIZATION" ID="U">
      <mets:name>UUB, Uppsala universitetsbibliotek</mets:name>
    </mets:agent>
  </mets:metsHdr>
  <mets:dmdSec ID="image_1271" CREATED="2014-05-16T10:57:00">
    <mets:mdWrap MDTYPE="OTHER">
      <mets:xmlData>
        <pagegroup xsi:noNamespaceSchemaLocation="http://www.ub.gu.se/handskriftsdatabasen/api/imagedata.xsd">
          <imagedata hd-id="1271" hd-ref="bild">
            <physdesc>4 bl., 1 kuvert</physdesc>
            <note>Kattresan (Lillans kattresa) i engelsk översättning, odat.</note>
            <userestrict>1</userestrict>
          </imagedata>
        </pagegroup>
      </mets:xmlData>
    </mets:mdWrap>
  </mets:dmdSec>
  <mets:dmdSec ID="image_1272" CREATED="2014-05-16T10:57:00">
    <mets:mdWrap MDTYPE="OTHER">
      <mets:xmlData>
        <pagegroup xsi:noNamespaceSchemaLocation="http://www.ub.gu.se/handskriftsdatabasen/api/imagedata.xsd">
          <imagedata hd-id="1272" hd-ref="bild">
            <physdesc>1 bl.</physdesc>
            <note>Lillans månresa i engelsk tolkning, 1919. (ingår i ett brev)</note>
            <userestrict>1</userestrict>
          </imagedata>
        </pagegroup>
      </mets:xmlData>
    </mets:mdWrap>
  </mets:dmdSec>
  <mets:dmdSec ID="image_1273" CREATED="2014-05-16T10:57:00">
    <mets:mdWrap MDTYPE="OTHER">
      <mets:xmlData>
        <pagegroup xsi:noNamespaceSchemaLocation="http://www.ub.gu.se/handskriftsdatabasen/api/imagedata.xsd">
          <imagedata hd-id="1273" hd-ref="bild">
            <physdesc>2 bl, 1 visitkort</physdesc>
            <note>Lillans månresa i tysk tolkning, odat.</note>
            <userestrict>1</userestrict>
          </imagedata>
        </pagegroup>
      </mets:xmlData>
    </mets:mdWrap>
  </mets:dmdSec>
  <mets:dmdSec ID="dmdSec1" CREATED="2014-05-16T10:57:00">
    <mets:mdWrap MDTYPE="OTHER">
      <mets:xmlData>
        <gubs>
          <manuscript xmlns:xsi="http://www.w3.org/2001/XMLSchema-instance" hd-id="2621" hd-ref="dokument" xsi:noNamespaceSchemaLocation="http://www.ub.gu.se/handskriftsdatabasen/api/schema.xsd">
            <archive hd-id="21" hd-ref="arkiv">
              <unittitle>Handlingar rörande konstnären Ivar Arosenius</unittitle>
              <unitdate>1896-2011</unitdate>
              <physloc>H 201</physloc>
              <physdesc>12 volymer</physdesc>
              <originator hd-id="1731" hd-ref="namn">
                <name-given>Ivar</name-given>
                <name-family>Arosenius</name-family>
                <name-date>1878-1909</name-date>
                <occupation hd-id="5" hd-ref="yrke">konstnär</occupation>
              </originator>
              <description>Ivar Arosenius föddes 1878 i Göteborg. Han studerade vid Slöjdföreningens skola och för Carl Wilhelmson på Valand.
Senare flyttade han till Stockholm och började på Konstakademien med Richard Berg som lärare.
1906 gifte han sig med Eva Adler och de bodde en kort tid i Åby utanför Norrköping. Det var här dottern Lillan föddes. 1907 flyttade familjen till Älvängen norr om Göteborg. Ivar Arosenius avled här 1909.
Handlingarna, som består av manuskriptböcker, fotografier, teckningar och brev, är en deposition av Kungliga Vetenskaps- och Vitterhetssamhället i Göteborg.
Material rörande Ivar Arosenius finns även i Nils Bonde Adlers samling, H 202.</description>
              <sigel hd-id="1" hd-ref="sigel">G</sigel>
            </archive>
            <document>
              <unittitle>Översättningar av Ivar Arosenius litterära verk</unittitle>
              <physloc>2</physloc>
              <physdesc>2 fasc.</physdesc>
              <searchdate>1969-1969</searchdate>
              <language hd-id="3" hd-ref="sprak">Svenska</language>
              <genreform hd-id="1" hd-ref="kategori">Manuskript</genreform>
              <genre hd-id="1" hd-ref="genre">Lyrik</genre>
              <originator hd-id="1731" hd-ref="namn">
                <name-given>Ivar</name-given>
                <name-family>Arosenius</name-family>
                <name-date>1878-1909</name-date>
                <occupation hd-id="5" hd-ref="yrke">konstnär</occupation>
                <role hd-id="11" hd-ref="funktion">Författare</role>
              </originator>
              <titleinformation>
                <title>Översättningar av Ivar Arosenius litterära verk</title>
              </titleinformation>
              <note>Kattresan (Lillans kattresa) i engelsk översättning, odat; Lillans månresa i tysk och engelsk tolkning, 1969, odat.</note>
              <data>
                <imagedata hd-id="1271" hd-ref="bild">
                  <physdesc>4 bl., 1 kuvert</physdesc>
                  <note>Kattresan (Lillans kattresa) i engelsk översättning, odat.</note>
                  <userestrict>1</userestrict>
                </imagedata>
                <imagedata hd-id="1272" hd-ref="bild">
                  <physdesc>1 bl.</physdesc>
                  <note>Lillans månresa i engelsk tolkning, 1919. (ingår i ett brev)</note>
                  <userestrict>1</userestrict>
                </imagedata>
                <imagedata hd-id="1273" hd-ref="bild">
                  <physdesc>2 bl, 1 visitkort</physdesc>
                  <note>Lillans månresa i tysk tolkning, odat.</note>
                  <userestrict>1</userestrict>
                </imagedata>
              </data>
            </document>
          </manuscript>
        </gubs>
      </mets:xmlData>
    </mets:mdWrap>
  </mets:dmdSec>
  <mets:amdSec ID="amdSec1">
    <mets:rightsMD ID="rightsDM1">
      <mets:mdWrap MDTYPE="OTHER">
        <mets:xmlData>
          <copyright copyright.status="pd" publication.status="unpublished" xsi:noNamespaceSchemaLocation="http://www.cdlib.org/groups/rmg/docs/copyrightMD.xsd"/>
        </mets:xmlData>
      </mets:mdWrap>
    </mets:rightsMD>
  </mets:amdSec>
  <mets:fileSec ID="fileSec1">
    <mets:fileGrp USE="master">
      <mets:file ID="master0001" MIMETYPE="image/tiff" CHECKSUMTYPE="SHA-512" CHECKSUM="f0a5ec144a3eaffcbf22ddc337ab2a90799f77481c1980f9642d00c3f633d8120dd37eb5764ac9ae3c3cf68a3a8ab076dfffe50cc81c6eea9876b0cb45515a87">
        <mets:FLocat LOCTYPE="URL" xlink:href="master/0001.tif"/>
      </mets:file>
      <mets:file ID="master0002" MIMETYPE="image/tiff" CHECKSUMTYPE="SHA-512" CHECKSUM="d81aa54bcdc7aff85e9bcfe304efe9f90588e2db4b994a5f8ff9a74f73e5e2f4a467c525b798c90c4ffec45028601c8bcde33da695cc297b9d3b59358c205542">
        <mets:FLocat LOCTYPE="URL" xlink:href="master/0002.tif"/>
      </mets:file>
      <mets:file ID="master0003" MIMETYPE="image/tiff" CHECKSUMTYPE="SHA-512" CHECKSUM="37c08b514be39449322efe1469eb024d7fd152f424c05586d8da99382473925f0d3607ef4f1641f0d80b54dc99830b52ceaf38eb5762f679fb245cde0267d09d">
        <mets:FLocat LOCTYPE="URL" xlink:href="master/0003.tif"/>
      </mets:file>
      <mets:file ID="master0004" MIMETYPE="image/tiff" CHECKSUMTYPE="SHA-512" CHECKSUM="4e85726cdbdd6fe38f3e49ead6ec39df0e4092294ffa52bad35e31efaa717b675e1ff2404cf63f38047bb72a6d0d0e5568d096833fb9f772456a361ca9b789be">
        <mets:FLocat LOCTYPE="URL" xlink:href="master/0004.tif"/>
      </mets:file>
      <mets:file ID="master0005" MIMETYPE="image/tiff" CHECKSUMTYPE="SHA-512" CHECKSUM="49bdc47290ce37444583f445d8f721d1e8eb6fe42e37788d258760d97bda30b8cb037e5d456e8dbf373d770ebec88aad693e2ca37ee3b71ce7e064152a93dc63">
        <mets:FLocat LOCTYPE="URL" xlink:href="master/0005.tif"/>
      </mets:file>
      <mets:file ID="master0006" MIMETYPE="image/tiff" CHECKSUMTYPE="SHA-512" CHECKSUM="05f945e0e2806fa7750df4258285808706e1a166318d952e2213f6fc1704ce80e9f9fe370effb8963f9df58f82d22550e1985f63e484a157587c174b6f365233">
        <mets:FLocat LOCTYPE="URL" xlink:href="master/0006.tif"/>
      </mets:file>
      <mets:file ID="master0007" MIMETYPE="image/tiff" CHECKSUMTYPE="SHA-512" CHECKSUM="60bc1da81c55c489c33754277694ea93f55acd9a8d424d45bc385fd8ee536fff4e92421ff3716900f043d54073e2fd5f0f6c9d206d8c88d464d08093b243a959">
        <mets:FLocat LOCTYPE="URL" xlink:href="master/0007.tif"/>
      </mets:file>
      <mets:file ID="master0008" MIMETYPE="image/tiff" CHECKSUMTYPE="SHA-512" CHECKSUM="20c6a1994bcf3ebe392054f5f9e5a4a08b66da0b5a2dd652913a3eef02129e6151184e127c4ad811dcb9291600fcd7b080b0492bfb985c097ebb306eab2ebcb8">
        <mets:FLocat LOCTYPE="URL" xlink:href="master/0008.tif"/>
      </mets:file>
      <mets:file ID="master0009" MIMETYPE="image/tiff" CHECKSUMTYPE="SHA-512" CHECKSUM="da2221fe84771217ee277773e1e4096933911190dddefacbfb938749f1dd4c59084b3dc284dc3cfec4b6e91adbecf37e82aa36a754d5476b8aa5940de8bcac4d">
        <mets:FLocat LOCTYPE="URL" xlink:href="master/0009.tif"/>
      </mets:file>
      <mets:file ID="master0010" MIMETYPE="image/tiff" CHECKSUMTYPE="SHA-512" CHECKSUM="fb7165c0d0474ee5416388902c4868e8e0cff5da82a5c8ecb92bb903895fbf0c0c15d1b05f00ac7cc85e9a0e2d0288e152967fe96605231ef2c6ecf35a891508">
        <mets:FLocat LOCTYPE="URL" xlink:href="master/0010.tif"/>
      </mets:file>
      <mets:file ID="master0011" MIMETYPE="image/tiff" CHECKSUMTYPE="SHA-512" CHECKSUM="e5a065542e0d8eae857bf08e25d9d771b17ceb67c76371f7d692d178dd3f28fd1d25e413f461b9f059dfbff557df2f0670cc363e8551324153ecc641767d925e">
        <mets:FLocat LOCTYPE="URL" xlink:href="master/0011.tif"/>
      </mets:file>
      <mets:file ID="master0012" MIMETYPE="image/tiff" CHECKSUMTYPE="SHA-512" CHECKSUM="9fa756c52f93badb6ecd8be60605153692ae5d5110ef7b428db0f091d50c23a708f3b1e550aa1dc7ab5c8b3f78f50ce548228db78f944a227a24174140745244">
        <mets:FLocat LOCTYPE="URL" xlink:href="master/0012.tif"/>
      </mets:file>
      <mets:file ID="master0013" MIMETYPE="image/tiff" CHECKSUMTYPE="SHA-512" CHECKSUM="4cb09ff41eb2420ff0e03d1925be8239dbf46f7c643f84b6dc34e30ad976ae169590c401c02be894f60ece15107c4dc4f09d1a1155c053e8c43efec9f1726801">
        <mets:FLocat LOCTYPE="URL" xlink:href="master/0013.tif"/>
      </mets:file>
      <mets:file ID="master0014" MIMETYPE="image/tiff" CHECKSUMTYPE="SHA-512" CHECKSUM="bd7dbf2b0b17e76f8be4a33076d9e518cd9dd9d58303d78257ff06e84ed50756f1c316c02e1e91e3fd9fe16766732b23d257f76bba8d8bd42d0f3266869cf9d6">
        <mets:FLocat LOCTYPE="URL" xlink:href="master/0014.tif"/>
      </mets:file>
      <mets:file ID="master0015" MIMETYPE="image/tiff" CHECKSUMTYPE="SHA-512" CHECKSUM="84600ab5ee3960d9f263d684ff0724df0a910573d7f4378f9ec8d85563179b92c165be66f085e53dda895127af36f32c9bc3f0d5204479378d36527b191d7ade">
        <mets:FLocat LOCTYPE="URL" xlink:href="master/0015.tif"/>
      </mets:file>
      <mets:file ID="master0016" MIMETYPE="image/tiff" CHECKSUMTYPE="SHA-512" CHECKSUM="27330949a1b7f63357e62860181dabf7e7f47b61c076774986d83754c35f6a2db0046422f0b00012cfc8fa6397f7902f3ebb7eefe740eab1a929595efc01cc19">
        <mets:FLocat LOCTYPE="URL" xlink:href="master/0016.tif"/>
      </mets:file>
      <mets:file ID="master0017" MIMETYPE="image/tiff" CHECKSUMTYPE="SHA-512" CHECKSUM="b29a0ecdd9b9b51473e365fa2b7a2b9c20a96b603618f7e5fcb7f10b04d18bdc81d328fd74311d7a765f5e8886a785adaf42af592a2e07649a054d34ba08bb01">
        <mets:FLocat LOCTYPE="URL" xlink:href="master/0017.tif"/>
      </mets:file>
      <mets:file ID="master0018" MIMETYPE="image/tiff" CHECKSUMTYPE="SHA-512" CHECKSUM="a72444ac75d1d266ffe7b58fb6c624e2779ca8b080d1bd9fd9b453f04ba979389234cbf7469aac8e9ae6f5ffa083542e5f886ccdab5a21e6b1eff4d244720f24">
        <mets:FLocat LOCTYPE="URL" xlink:href="master/0018.tif"/>
      </mets:file>
      <mets:file ID="master0019" MIMETYPE="image/tiff" CHECKSUMTYPE="SHA-512" CHECKSUM="249c545f7e21323220291f97c1fa4248c521f3e05e29894c945299cd04a2c1e9d6c48be670e58e180cab4cf05e38376d41320bf2337788c7a6f28824314010de">
        <mets:FLocat LOCTYPE="URL" xlink:href="master/0019.tif"/>
      </mets:file>
    </mets:fileGrp>
    <mets:fileGrp USE="web">
      <mets:file ID="web0001" MIMETYPE="image/jpeg" CHECKSUMTYPE="SHA-512" CHECKSUM="2a843fe8f14865cba7ec1d8073f8522fb980b96303d0e8e0c978d6a9e47bbe8f7c8c4e904fab48feee3f036325dfbe3d707a84383c9a7a303bc32c4c5febae39">
        <mets:FLocat LOCTYPE="URL" xlink:href="web/0001.jpg"/>
      </mets:file>
      <mets:file ID="web0002" MIMETYPE="image/jpeg" CHECKSUMTYPE="SHA-512" CHECKSUM="b788afa63c1c475126fa1a833f4bbc643645c07f28b0eab444cfadeb37dac0af51fd82373798bf9ea2bfef0e251d4c92f0b7b8274ca55d24d0947d488ed40459">
        <mets:FLocat LOCTYPE="URL" xlink:href="web/0002.jpg"/>
      </mets:file>
      <mets:file ID="web0003" MIMETYPE="image/jpeg" CHECKSUMTYPE="SHA-512" CHECKSUM="de41d449456b4861ee474399ddc24752a43485f9515e7e9915ba68a80e6c40122eff7dfc0f65ccbb2357ce03d744423a28248bb51dc1a3646baec3d53ac00ce6">
        <mets:FLocat LOCTYPE="URL" xlink:href="web/0003.jpg"/>
      </mets:file>
      <mets:file ID="web0004" MIMETYPE="image/jpeg" CHECKSUMTYPE="SHA-512" CHECKSUM="ac398b5abf5ba2c2f4bad31c6206a1d543cbff1093978de35b454c5a869a609c96f2d0c78dab72507555ab17d9e4f1676201dc790090d88ed382c3459689eb56">
        <mets:FLocat LOCTYPE="URL" xlink:href="web/0004.jpg"/>
      </mets:file>
      <mets:file ID="web0005" MIMETYPE="image/jpeg" CHECKSUMTYPE="SHA-512" CHECKSUM="c9c9a088e2dac12ea83d4ccd5fe3a4ec47c2f0645da71a1ae0016157c2b4e6cfc06b169d2d082a1c3aa2cd01d5fc18ca1da434b68bee491a6a1529c14bca0711">
        <mets:FLocat LOCTYPE="URL" xlink:href="web/0005.jpg"/>
      </mets:file>
      <mets:file ID="web0006" MIMETYPE="image/jpeg" CHECKSUMTYPE="SHA-512" CHECKSUM="1e5e5882db1c84288aab804c6bf88787ca93555be89e457f1dc335f629ad86b8822ca30efca7c64a65ff6fcedf81aa205556452ed06734ed64f1fbf462ee5ced">
        <mets:FLocat LOCTYPE="URL" xlink:href="web/0006.jpg"/>
      </mets:file>
      <mets:file ID="web0007" MIMETYPE="image/jpeg" CHECKSUMTYPE="SHA-512" CHECKSUM="6b1e6a79a8b52295b67cc0253bb577eb59faece98aecaf9a36d54000404e6e66ec86cb709de78dbf5c923fd7f06ae7514856e39f63cda1188aea938020ddbfa9">
        <mets:FLocat LOCTYPE="URL" xlink:href="web/0007.jpg"/>
      </mets:file>
      <mets:file ID="web0008" MIMETYPE="image/jpeg" CHECKSUMTYPE="SHA-512" CHECKSUM="c4dae2d3a4ad6892584e686ab039fbe2f11d1d17f09a0cf49250c7906d6ecfe8bf6af7544f1bb693a95e0f95849e9fc5c6cd585ff65e781e5756a49847c70a9e">
        <mets:FLocat LOCTYPE="URL" xlink:href="web/0008.jpg"/>
      </mets:file>
      <mets:file ID="web0009" MIMETYPE="image/jpeg" CHECKSUMTYPE="SHA-512" CHECKSUM="16e593798b5e157c30250d27e9feea97f51e869f65516bce808a47b5ab94c20c4a11038456257c7e353a02cb3d66ae110817338e3e196077a5cf065f3bcf57d1">
        <mets:FLocat LOCTYPE="URL" xlink:href="web/0009.jpg"/>
      </mets:file>
      <mets:file ID="web0010" MIMETYPE="image/jpeg" CHECKSUMTYPE="SHA-512" CHECKSUM="c88964941548a410d1300421bd354663b487c1a0ec75fbabbb8b332cacdcfd17dd0b8ae5bb9a1ab04e42924aa57982971bd58720550dbd91fca44418853352bd">
        <mets:FLocat LOCTYPE="URL" xlink:href="web/0010.jpg"/>
      </mets:file>
      <mets:file ID="web0011" MIMETYPE="image/jpeg" CHECKSUMTYPE="SHA-512" CHECKSUM="7b741d0c9e54223ab5ab2dfa54d0ed09521c44528a7ab6ab939a963a71a0c64815613cf808e1d796ace5112e5a7dcbd4eeb1c7f1c35be6a34093918aef4cf168">
        <mets:FLocat LOCTYPE="URL" xlink:href="web/0011.jpg"/>
      </mets:file>
      <mets:file ID="web0012" MIMETYPE="image/jpeg" CHECKSUMTYPE="SHA-512" CHECKSUM="95d1987aac6415ae7f11f720bd6483132808f1d366aacaaa4b9f6eef36acf8f9f857efab4cba2aca2dc9c7f8abeb2b7a081a9e1d93aec312f0c67d4c2a00d7d8">
        <mets:FLocat LOCTYPE="URL" xlink:href="web/0012.jpg"/>
      </mets:file>
      <mets:file ID="web0013" MIMETYPE="image/jpeg" CHECKSUMTYPE="SHA-512" CHECKSUM="b3d88697582512051b3c0274d0333faa54ce89584e5e93aef69d726fc36b6a1c529c04b76c181bdd50c651fac6168f5ba2e0f6f6034672919b9048dd0f942c04">
        <mets:FLocat LOCTYPE="URL" xlink:href="web/0013.jpg"/>
      </mets:file>
      <mets:file ID="web0014" MIMETYPE="image/jpeg" CHECKSUMTYPE="SHA-512" CHECKSUM="4cfc56609557f29a750c2d8d29e52c46e3daa90e72da619f36679ea47ed42b352e7494516ce339708053ea4c018c30cb815bd4c08f38e006d21aab7f3338ef42">
        <mets:FLocat LOCTYPE="URL" xlink:href="web/0014.jpg"/>
      </mets:file>
      <mets:file ID="web0015" MIMETYPE="image/jpeg" CHECKSUMTYPE="SHA-512" CHECKSUM="678ae36e61ad6ba1f62b3dcba07cfdb0cc3efadf87003293ce4053fbb15fcc3c0bd9cd76023fd4a588de41ac6b81ac85d5bf9c1ec9cd92f37d3550eb8c600426">
        <mets:FLocat LOCTYPE="URL" xlink:href="web/0015.jpg"/>
      </mets:file>
      <mets:file ID="web0016" MIMETYPE="image/jpeg" CHECKSUMTYPE="SHA-512" CHECKSUM="93ab3c8b8c6c1b4d4697c84ac65b13827a873f820cfaaacb4e3c0071b256ede18aab6cdd19ad36f71e6bbbbe67c25cb77355fd30d34043ad8dab77a5dd9c6808">
        <mets:FLocat LOCTYPE="URL" xlink:href="web/0016.jpg"/>
      </mets:file>
      <mets:file ID="web0017" MIMETYPE="image/jpeg" CHECKSUMTYPE="SHA-512" CHECKSUM="c7836fad32541d5742a3fcb6bb78cba777dd1f4da004a55da904f518f268c926224967fe712d404994250c363186da031057c7104465309d427722cfe797e9a6">
        <mets:FLocat LOCTYPE="URL" xlink:href="web/0017.jpg"/>
      </mets:file>
      <mets:file ID="web0018" MIMETYPE="image/jpeg" CHECKSUMTYPE="SHA-512" CHECKSUM="36bac9a42363ef5a073c135420983b7c24e474c615bf9dd9a7dca7d68a66a1e02ad0e2d2ff212495bb440014eba5cd0c5ada007f14d8e50c15e445bde9365279">
        <mets:FLocat LOCTYPE="URL" xlink:href="web/0018.jpg"/>
      </mets:file>
      <mets:file ID="web0019" MIMETYPE="image/jpeg" CHECKSUMTYPE="SHA-512" CHECKSUM="06b6733dea1361ef2a992800b4e6c6ac930b87bc57dad7ce2ee8c168bbe21198c53fb08881db019dc1d2c19ceb0df6e67ada53196032c6a173236fba55dad96e">
        <mets:FLocat LOCTYPE="URL" xlink:href="web/0019.jpg"/>
      </mets:file>
    </mets:fileGrp>
    <mets:fileGrp USE="alto">
      <mets:file ID="alto0001" MIMETYPE="text/xml" CHECKSUMTYPE="SHA-512" CHECKSUM="c4bfe2650861898d01623fac51baef82db633ad38acf59573ac8e9eefc9ab81f3b8eebdd0a9c80ff59ba976c54e6b13e587c73b664d7c4490cfb5e161f9c29d8">
        <mets:FLocat LOCTYPE="URL" xlink:href="alto/0001.xml"/>
      </mets:file>
      <mets:file ID="alto0002" MIMETYPE="text/xml" CHECKSUMTYPE="SHA-512" CHECKSUM="c4bfe2650861898d01623fac51baef82db633ad38acf59573ac8e9eefc9ab81f3b8eebdd0a9c80ff59ba976c54e6b13e587c73b664d7c4490cfb5e161f9c29d8">
        <mets:FLocat LOCTYPE="URL" xlink:href="alto/0002.xml"/>
      </mets:file>
      <mets:file ID="alto0003" MIMETYPE="text/xml" CHECKSUMTYPE="SHA-512" CHECKSUM="a60a80f5ab84c6b43850529be9b36706a07355648139a157e41f181933b1dbb426d97f449eb364cd61309d9256b8967c9e0b8968b4fafc8585f2238c5aed3891">
        <mets:FLocat LOCTYPE="URL" xlink:href="alto/0003.xml"/>
      </mets:file>
      <mets:file ID="alto0004" MIMETYPE="text/xml" CHECKSUMTYPE="SHA-512" CHECKSUM="59e2ceb3fbd04059414dc8f6c5d11a7f80e3a083e7c0e44bc45c71004bc82c52bc5db79e49d20b7fbbc4e969e3959bf59a446336f402195e8313a711fb788d5a">
        <mets:FLocat LOCTYPE="URL" xlink:href="alto/0004.xml"/>
      </mets:file>
      <mets:file ID="alto0005" MIMETYPE="text/xml" CHECKSUMTYPE="SHA-512" CHECKSUM="c4bfe2650861898d01623fac51baef82db633ad38acf59573ac8e9eefc9ab81f3b8eebdd0a9c80ff59ba976c54e6b13e587c73b664d7c4490cfb5e161f9c29d8">
        <mets:FLocat LOCTYPE="URL" xlink:href="alto/0005.xml"/>
      </mets:file>
      <mets:file ID="alto0006" MIMETYPE="text/xml" CHECKSUMTYPE="SHA-512" CHECKSUM="59e2ceb3fbd04059414dc8f6c5d11a7f80e3a083e7c0e44bc45c71004bc82c52bc5db79e49d20b7fbbc4e969e3959bf59a446336f402195e8313a711fb788d5a">
        <mets:FLocat LOCTYPE="URL" xlink:href="alto/0006.xml"/>
      </mets:file>
      <mets:file ID="alto0007" MIMETYPE="text/xml" CHECKSUMTYPE="SHA-512" CHECKSUM="c4bfe2650861898d01623fac51baef82db633ad38acf59573ac8e9eefc9ab81f3b8eebdd0a9c80ff59ba976c54e6b13e587c73b664d7c4490cfb5e161f9c29d8">
        <mets:FLocat LOCTYPE="URL" xlink:href="alto/0007.xml"/>
      </mets:file>
      <mets:file ID="alto0008" MIMETYPE="text/xml" CHECKSUMTYPE="SHA-512" CHECKSUM="59e2ceb3fbd04059414dc8f6c5d11a7f80e3a083e7c0e44bc45c71004bc82c52bc5db79e49d20b7fbbc4e969e3959bf59a446336f402195e8313a711fb788d5a">
        <mets:FLocat LOCTYPE="URL" xlink:href="alto/0008.xml"/>
      </mets:file>
      <mets:file ID="alto0009" MIMETYPE="text/xml" CHECKSUMTYPE="SHA-512" CHECKSUM="c4bfe2650861898d01623fac51baef82db633ad38acf59573ac8e9eefc9ab81f3b8eebdd0a9c80ff59ba976c54e6b13e587c73b664d7c4490cfb5e161f9c29d8">
        <mets:FLocat LOCTYPE="URL" xlink:href="alto/0009.xml"/>
      </mets:file>
      <mets:file ID="alto0010" MIMETYPE="text/xml" CHECKSUMTYPE="SHA-512" CHECKSUM="f9b5c47a3073ca366d8f52b987e9b8818366492ad67605ab40343caec91d7429b3ca063b17129d2b4d8c14ab7d6a93ff9118999c87bac4c3a65d13beac64ff85">
        <mets:FLocat LOCTYPE="URL" xlink:href="alto/0010.xml"/>
      </mets:file>
      <mets:file ID="alto0011" MIMETYPE="text/xml" CHECKSUMTYPE="SHA-512" CHECKSUM="8f85de9fc305c9b2d74e3d6128133a80bb610796658ec05e6c068d1a7ef7489875445a849f9d424ab584ad3d30a06b771a8d769ed4c4790dccf2f1f1459db6f2">
        <mets:FLocat LOCTYPE="URL" xlink:href="alto/0011.xml"/>
      </mets:file>
      <mets:file ID="alto0012" MIMETYPE="text/xml" CHECKSUMTYPE="SHA-512" CHECKSUM="17c858ae252fccbaa81c80b05b3ceff3d5347477347735ef919e3493559d95e589ba7d78c24e48f4c40b12102fce72441141283baa5ab5fba8884e73975d408e">
        <mets:FLocat LOCTYPE="URL" xlink:href="alto/0012.xml"/>
      </mets:file>
      <mets:file ID="alto0013" MIMETYPE="text/xml" CHECKSUMTYPE="SHA-512" CHECKSUM="bbffb6f5f35457fa4a725aa7c21c62c938bfe83909a6a2efe940c6af89e821f32b7d040c6c0ae7ebbf75f7ec05812ba9120bb81e2660df45a94251619caadad5">
        <mets:FLocat LOCTYPE="URL" xlink:href="alto/0013.xml"/>
      </mets:file>
      <mets:file ID="alto0014" MIMETYPE="text/xml" CHECKSUMTYPE="SHA-512" CHECKSUM="9f8638349cf173e4bfe18e94d87191f9677cc9e63ba4c07acc53577a0a399b6786f35c4dd41d4daa2f75e3900faf68698a6ff525815919344d712e1a342b786f">
        <mets:FLocat LOCTYPE="URL" xlink:href="alto/0014.xml"/>
      </mets:file>
      <mets:file ID="alto0015" MIMETYPE="text/xml" CHECKSUMTYPE="SHA-512" CHECKSUM="9f8638349cf173e4bfe18e94d87191f9677cc9e63ba4c07acc53577a0a399b6786f35c4dd41d4daa2f75e3900faf68698a6ff525815919344d712e1a342b786f">
        <mets:FLocat LOCTYPE="URL" xlink:href="alto/0015.xml"/>
      </mets:file>
      <mets:file ID="alto0016" MIMETYPE="text/xml" CHECKSUMTYPE="SHA-512" CHECKSUM="2bb0f5a8637eb56f3c3f29a3458d5ca30e8a5dd825541a7cff3b7c1c13e8f4faf138426d36e8b73a5d7911c52f5f48916a2efad7241bac23a5942542f8fbc810">
        <mets:FLocat LOCTYPE="URL" xlink:href="alto/0016.xml"/>
      </mets:file>
      <mets:file ID="alto0017" MIMETYPE="text/xml" CHECKSUMTYPE="SHA-512" CHECKSUM="2bb0f5a8637eb56f3c3f29a3458d5ca30e8a5dd825541a7cff3b7c1c13e8f4faf138426d36e8b73a5d7911c52f5f48916a2efad7241bac23a5942542f8fbc810">
        <mets:FLocat LOCTYPE="URL" xlink:href="alto/0017.xml"/>
      </mets:file>
      <mets:file ID="alto0018" MIMETYPE="text/xml" CHECKSUMTYPE="SHA-512" CHECKSUM="0eb84434f439c5338b5728ff19bc3d1df33fa787b617cfaf0dc1dca127b6c5451a32aafbe9ac8faa2a8e3819437ad7315baf4f395e90b5c729e3b81c52c4b9b6">
        <mets:FLocat LOCTYPE="URL" xlink:href="alto/0018.xml"/>
      </mets:file>
      <mets:file ID="alto0019" MIMETYPE="text/xml" CHECKSUMTYPE="SHA-512" CHECKSUM="0eb84434f439c5338b5728ff19bc3d1df33fa787b617cfaf0dc1dca127b6c5451a32aafbe9ac8faa2a8e3819437ad7315baf4f395e90b5c729e3b81c52c4b9b6">
        <mets:FLocat LOCTYPE="URL" xlink:href="alto/0019.xml"/>
      </mets:file>
    </mets:fileGrp>
    <mets:fileGrp USE="pdf">
      <mets:file ID="pdfGUB0102021" MIMETYPE="text/pdf" CHECKSUMTYPE="SHA-512" CHECKSUM="f9ca942951f372f4b9054ac73f7754c97650272626313b63f37c5f7a639006e3856fb6e571310129060e5ad8e18a01d234e65f3c4c75fd5ac8f824b5462f66a0">
        <mets:FLocat LOCTYPE="URL" xlink:href="pdf/GUB0102021.pdf"/>
      </mets:file>
    </mets:fileGrp>
  </mets:fileSec>
  <mets:structMap TYPE="Physical">
    <mets:div TYPE="Monograph">
      <mets:div TYPE="ColorTarget" ID="physical_divpage1" ORDER="1">
        <mets:fptr FILEID="master0001"/>
        <mets:fptr FILEID="web0001"/>
        <mets:fptr FILEID="alto0001"/>
      </mets:div>
      <mets:div TYPE="RightPage" ID="physical_divpage2" ORDER="2">
        <mets:fptr FILEID="master0002"/>
        <mets:fptr FILEID="web0002"/>
        <mets:fptr FILEID="alto0002"/>
      </mets:div>
      <mets:div TYPE="LeftPage" ID="physical_divpage3" ORDER="3">
        <mets:fptr FILEID="master0003"/>
        <mets:fptr FILEID="web0003"/>
        <mets:fptr FILEID="alto0003"/>
      </mets:div>
      <mets:div TYPE="RightPage" ID="physical_divpage4" ORDER="4">
        <mets:fptr FILEID="master0004"/>
        <mets:fptr FILEID="web0004"/>
        <mets:fptr FILEID="alto0004"/>
      </mets:div>
      <mets:div TYPE="LeftPage" ID="physical_divpage5" ORDER="5">
        <mets:fptr FILEID="master0005"/>
        <mets:fptr FILEID="web0005"/>
        <mets:fptr FILEID="alto0005"/>
      </mets:div>
      <mets:div TYPE="RightPage" ID="physical_divpage6" ORDER="6">
        <mets:fptr FILEID="master0006"/>
        <mets:fptr FILEID="web0006"/>
        <mets:fptr FILEID="alto0006"/>
      </mets:div>
      <mets:div TYPE="LeftPage" ID="physical_divpage7" ORDER="7">
        <mets:fptr FILEID="master0007"/>
        <mets:fptr FILEID="web0007"/>
        <mets:fptr FILEID="alto0007"/>
      </mets:div>
      <mets:div TYPE="RightPage" ID="physical_divpage8" ORDER="8">
        <mets:fptr FILEID="master0008"/>
        <mets:fptr FILEID="web0008"/>
        <mets:fptr FILEID="alto0008"/>
      </mets:div>
      <mets:div TYPE="LeftPage" ID="physical_divpage9" ORDER="9">
        <mets:fptr FILEID="master0009"/>
        <mets:fptr FILEID="web0009"/>
        <mets:fptr FILEID="alto0009"/>
      </mets:div>
      <mets:div TYPE="RightPage" ID="physical_divpage10" ORDER="10">
        <mets:fptr FILEID="master0010"/>
        <mets:fptr FILEID="web0010"/>
        <mets:fptr FILEID="alto0010"/>
      </mets:div>
      <mets:div TYPE="LeftPage" ID="physical_divpage11" ORDER="11">
        <mets:fptr FILEID="master0011"/>
        <mets:fptr FILEID="web0011"/>
        <mets:fptr FILEID="alto0011"/>
      </mets:div>
      <mets:div TYPE="RightPage" ID="physical_divpage12" ORDER="12">
        <mets:fptr FILEID="master0012"/>
        <mets:fptr FILEID="web0012"/>
        <mets:fptr FILEID="alto0012"/>
      </mets:div>
      <mets:div TYPE="LeftPage" ID="physical_divpage13" ORDER="13">
        <mets:fptr FILEID="master0013"/>
        <mets:fptr FILEID="web0013"/>
        <mets:fptr FILEID="alto0013"/>
      </mets:div>
      <mets:div TYPE="RightPage" ID="physical_divpage14" ORDER="14">
        <mets:fptr FILEID="master0014"/>
        <mets:fptr FILEID="web0014"/>
        <mets:fptr FILEID="alto0014"/>
      </mets:div>
      <mets:div TYPE="LeftPage" ID="physical_divpage15" ORDER="15">
        <mets:fptr FILEID="master0015"/>
        <mets:fptr FILEID="web0015"/>
        <mets:fptr FILEID="alto0015"/>
      </mets:div>
      <mets:div TYPE="RightPage" ID="physical_divpage16" ORDER="16">
        <mets:fptr FILEID="master0016"/>
        <mets:fptr FILEID="web0016"/>
        <mets:fptr FILEID="alto0016"/>
      </mets:div>
      <mets:div TYPE="LeftPage" ID="physical_divpage17" ORDER="17">
        <mets:fptr FILEID="master0017"/>
        <mets:fptr FILEID="web0017"/>
        <mets:fptr FILEID="alto0017"/>
      </mets:div>
      <mets:div TYPE="RightPage" ID="physical_divpage18" ORDER="18">
        <mets:fptr FILEID="master0018"/>
        <mets:fptr FILEID="web0018"/>
        <mets:fptr FILEID="alto0018"/>
      </mets:div>
      <mets:div TYPE="LeftPage" ID="physical_divpage19" ORDER="19">
        <mets:fptr FILEID="master0019"/>
        <mets:fptr FILEID="web0019"/>
        <mets:fptr FILEID="alto0019"/>
      </mets:div>
    </mets:div>
  </mets:structMap>
  <mets:structMap TYPE="Logical">
    <mets:div TYPE="Monograph">
      <mets:div TYPE="Undefined" ID="logical_divpage1" ORDER="1" DMDID="image_1271">
        <mets:fptr FILEID="master0001"/>
        <mets:fptr FILEID="web0001"/>
        <mets:fptr FILEID="alto0001"/>
      </mets:div>
      <mets:div TYPE="Undefined" ID="logical_divpage2" ORDER="2" DMDID="image_1271">
        <mets:fptr FILEID="master0002"/>
        <mets:fptr FILEID="web0002"/>
        <mets:fptr FILEID="alto0002"/>
      </mets:div>
      <mets:div TYPE="Undefined" ID="logical_divpage3" ORDER="3" DMDID="image_1271">
        <mets:fptr FILEID="master0003"/>
        <mets:fptr FILEID="web0003"/>
        <mets:fptr FILEID="alto0003"/>
      </mets:div>
      <mets:div TYPE="Undefined" ID="logical_divpage4" ORDER="4" DMDID="image_1271">
        <mets:fptr FILEID="master0004"/>
        <mets:fptr FILEID="web0004"/>
        <mets:fptr FILEID="alto0004"/>
      </mets:div>
      <mets:div TYPE="Undefined" ID="logical_divpage5" ORDER="5" DMDID="image_1271">
        <mets:fptr FILEID="master0005"/>
        <mets:fptr FILEID="web0005"/>
        <mets:fptr FILEID="alto0005"/>
      </mets:div>
      <mets:div TYPE="Undefined" ID="logical_divpage6" ORDER="6" DMDID="image_1271">
        <mets:fptr FILEID="master0006"/>
        <mets:fptr FILEID="web0006"/>
        <mets:fptr FILEID="alto0006"/>
      </mets:div>
      <mets:div TYPE="Undefined" ID="logical_divpage7" ORDER="7" DMDID="image_1271">
        <mets:fptr FILEID="master0007"/>
        <mets:fptr FILEID="web0007"/>
        <mets:fptr FILEID="alto0007"/>
      </mets:div>
      <mets:div TYPE="Undefined" ID="logical_divpage8" ORDER="8" DMDID="image_1271">
        <mets:fptr FILEID="master0008"/>
        <mets:fptr FILEID="web0008"/>
        <mets:fptr FILEID="alto0008"/>
      </mets:div>
      <mets:div TYPE="Undefined" ID="logical_divpage9" ORDER="9" DMDID="image_1271">
        <mets:fptr FILEID="master0009"/>
        <mets:fptr FILEID="web0009"/>
        <mets:fptr FILEID="alto0009"/>
      </mets:div>
      <mets:div TYPE="Undefined" ID="logical_divpage10" ORDER="10" DMDID="image_1271">
        <mets:fptr FILEID="master0010"/>
        <mets:fptr FILEID="web0010"/>
        <mets:fptr FILEID="alto0010"/>
      </mets:div>
      <mets:div TYPE="Undefined" ID="logical_divpage11" ORDER="11" DMDID="image_1271">
        <mets:fptr FILEID="master0011"/>
        <mets:fptr FILEID="web0011"/>
        <mets:fptr FILEID="alto0011"/>
      </mets:div>
      <mets:div TYPE="Undefined" ID="logical_divpage12" ORDER="12" DMDID="image_1272">
        <mets:fptr FILEID="master0012"/>
        <mets:fptr FILEID="web0012"/>
        <mets:fptr FILEID="alto0012"/>
      </mets:div>
      <mets:div TYPE="Undefined" ID="logical_divpage13" ORDER="13" DMDID="image_1272">
        <mets:fptr FILEID="master0013"/>
        <mets:fptr FILEID="web0013"/>
        <mets:fptr FILEID="alto0013"/>
      </mets:div>
      <mets:div TYPE="Undefined" ID="logical_divpage14" ORDER="14" DMDID="image_1273">
        <mets:fptr FILEID="master0014"/>
        <mets:fptr FILEID="web0014"/>
        <mets:fptr FILEID="alto0014"/>
      </mets:div>
      <mets:div TYPE="Undefined" ID="logical_divpage15" ORDER="15" DMDID="image_1273">
        <mets:fptr FILEID="master0015"/>
        <mets:fptr FILEID="web0015"/>
        <mets:fptr FILEID="alto0015"/>
      </mets:div>
      <mets:div TYPE="Undefined" ID="logical_divpage16" ORDER="16" DMDID="image_1273">
        <mets:fptr FILEID="master0016"/>
        <mets:fptr FILEID="web0016"/>
        <mets:fptr FILEID="alto0016"/>
      </mets:div>
      <mets:div TYPE="Undefined" ID="logical_divpage17" ORDER="17" DMDID="image_1273">
        <mets:fptr FILEID="master0017"/>
        <mets:fptr FILEID="web0017"/>
        <mets:fptr FILEID="alto0017"/>
      </mets:div>
      <mets:div TYPE="Undefined" ID="logical_divpage18" ORDER="18" DMDID="image_1273">
        <mets:fptr FILEID="master0018"/>
        <mets:fptr FILEID="web0018"/>
        <mets:fptr FILEID="alto0018"/>
      </mets:div>
      <mets:div TYPE="Undefined" ID="logical_divpage19" ORDER="19" DMDID="image_1273">
        <mets:fptr FILEID="master0019"/>
        <mets:fptr FILEID="web0019"/>
        <mets:fptr FILEID="alto0019"/>
      </mets:div>
    </mets:div>
  </mets:structMap>
</mets:mets>
